<annotation>
	<folder>cars on street</folder>
	<filename>87. 60b0f38b-a9e2-4f48-a482-bdc9dcfe6423.jpg</filename>
	<path>C:\Users\Lexie\Downloads\cars on street\87. 60b0f38b-a9e2-4f48-a482-bdc9dcfe6423.jpg</path>
	<source>
		<database>Unknown</database>
	</source>
	<size>
		<width>960</width>
		<height>640</height>
		<depth>3</depth>
	</size>
	<segmented>0</segmented>
	<object>
		<name>car</name>
		<pose>Unspecified</pose>
		<truncated>0</truncated>
		<difficult>0</difficult>
		<bndbox>
			<xmin>96</xmin>
			<ymin>125</ymin>
			<xmax>917</xmax>
			<ymax>513</ymax>
		</bndbox>
	</object>
</annotation>
